{"is_source_file": false, "format": "", "description": "", "external_files": [], "external_methods": [], "published": [], "classes": [], "methods": [], "calls": [], "search-terms": [], "state": 2, "file_id": 23, "knowledge_revision": 136, "git_revision": "e402d809cffbfe18b26df7b50f15bb771e40bb49", "hash": "d4df8a4334dfce74a31c9e256d6b80f5", "format-version": 4, "code-base-name": "pdf_to_ppt_frontend", "filename": "assets/emerald_theme_verification.md", "revision_history": [{"136": "e402d809cffbfe18b26df7b50f15bb771e40bb49"}]}